social_auth_app_cherrypy-1.0.0.dist-info/DESCRIPTION.rst
social_auth_app_cherrypy-1.0.0.dist-info/METADATA
social_auth_app_cherrypy-1.0.0.dist-info/RECORD
social_auth_app_cherrypy-1.0.0.dist-info/WHEEL
social_auth_app_cherrypy-1.0.0.dist-info/metadata.json
social_auth_app_cherrypy-1.0.0.dist-info/top_level.txt
social_cherrypy/__init__.py
social_cherrypy/models.py
social_cherrypy/strategy.py
social_cherrypy/utils.py
social_cherrypy/views.py
